OctoPrint_Slack-0.2.2.dist-info/DESCRIPTION.rst
OctoPrint_Slack-0.2.2.dist-info/METADATA
OctoPrint_Slack-0.2.2.dist-info/RECORD
OctoPrint_Slack-0.2.2.dist-info/WHEEL
OctoPrint_Slack-0.2.2.dist-info/entry_points.txt
OctoPrint_Slack-0.2.2.dist-info/metadata.json
OctoPrint_Slack-0.2.2.dist-info/top_level.txt
octoprint_slack/__init__.py
octoprint_slack/templates/slack_settings.jinja2
