Metadata-Version: 2.0
Name: OctoPrint-Slack
Version: 0.2.2
Summary: Slack integration for OctoPrint
Home-page: https://github.com/richjoyce/OctoPrint-Slack
Author: Richard Joyce
Author-email: rjoyce@rjoyce.me
License: MIT
Platform: UNKNOWN
Requires-Dist: OctoPrint
Requires-Dist: requests
